{"ok": true, "status": 200, "final_url": "https://news.pedaily.cn/202607/566448.shtml", "page_title": "「国测量子」完成超亿元Pre-B轮战略融资，加速“量子+行业”融合应用", "summary": "「国测量子」完成超亿元Pre-B轮战略融资，加速“量子+行业”融合应用,7月17日消息，国测量子近日完成超亿元Pre-B轮融资，由湖州锦坤等投资。资金将用于产品工程化与产业化及市场拓展，完善产品矩阵，推进技术攻关与应用落地。", "content": "国测量子科技（浙江）有限公司（以下简称“国测量子”）是由北京大学发起设立的量子精密测量产业化企业，公司聚焦量子传感与量子精密测量技术的自主创新和产业化应用，重点布局芯片原子钟、高端稳频激光器、量子磁力仪、特种激光器及量子时频系统等产品线。投资界（ID：pedaily2012）7月17日消息，近日，国测量子完成超亿元人民币Pre-B轮战略融资。本轮融资由湖州锦坤股权投资合伙企业（有限合伙）、湖州南太湖聚创股权投资合伙企业（有限合伙）共同投资。本轮募集资金将重点投向量子精密测量相关产品工程化与产业化能力建设以及量子精密测量应用市场拓展，进一步丰富国测量子量子精密测量产品矩阵，加快自主研发的量子科技产品及整体解决方案落地。\n国测量子长期深耕量子精密测量主赛道，坚持核心技术自主创新与产业化能力建设并重，围绕芯片原子钟、高端稳频激光器、量子磁力仪、特种激光器、量子时频系统等方向，持续推进关键技术攻关、产品工程化验证和规模化制造能力建设。\n在持续完善核心器件和整机产品布局的基础上，国测量子进一步提出“量子+”行业融合战略，重点构建“量子+通信”“量子+AI”“量子+电网”“量子+新能源”“量子+金融”“量子+装备”等系列解决方案。\n“量子+通信”：面向通信网络、卫星通信和下一代信息基础设施，为网络节点提供高精度同步、大容量/多信道吞吐、安全守时和时间基准保障能力；“量子+AI”：面向人工智能算力集群、智算中心和高性能计算系统，通过基于芯片原子钟边缘授时-守时一体化的高精度时频同步、低抖动时钟和可信时间戳，提升大规模算力节点协同效率及系统运行可靠性；“量子+电网”：面向新型电力系统、变电站和电力调度场景，提升关键节点时间同步、异常守时和复杂环境下持续运行能力；“量子+新能源”：面向风电、储能、微电网和零碳园区等场景，提供特种激光测量、高精度同步和智能感知能力，支撑新能源装备安全运行和精细化管理；“量子+金融”：面向银行、证券、交易系统和金融数据中心，在不改变现有主授时架构的基础上，构建端侧分布式守时和时间安全体系，提升金融信息系统的运行韧性；“量子+装备”：面向国防装备、海洋探测、航空航天及高端制造等领域，提供自主可控的量子传感、精密测量和特种激光产品。\n目前，公司已在浙江湖州、温州等地建设量子科技核心器件研发与批量制造基地，形成量子科技核心器件批产能力，持续提升关键产品自主保障和规模化交付水平。公司产品及解决方案广泛服务于算力基础设施、电力系统、人工智能、新一代通信技术、国防装备、海洋探测、航空航天、风力发电、金融基础设施等领域。\n国测量子表示，本轮融资资金将主要用于两大方向：一是持续加大核心技术和产品研发投入，进一步突破量子精密测量关键技术瓶颈，加快新一代产品研发、工程化验证和批量制造，持续推进现有产品性能提升与迭代升级；二是加快量子科技整体解决方案推广，推动量子精密测量核心器件、整机产品与重点行业基础设施深度融合，形成更多具有示范价值和复制推广能力的应用场景。\n文章来源：投资界原文地址：https://news.pedaily.cn/202607/566448.shtml\n清科控股（01945.HK）旗下创业与投资资讯平台", "published_time": "2026-07-17 10:17", "metrics": [], "paragraph_count": 8, "truncated": false, "fetched_at": "2026-07-17T15:01:05.592189+08:00", "cache_hit": false}