{"ok": true, "status": 200, "final_url": "http://www.ce.cn/xwzx/gnsz/gdxw/202607/t20260717_3092435.shtml", "page_title": "贵州重庆等地大到暴雨将成片出没 明起华北东北降雨再度增多_中国经济网——国家经济门户", "summary": "贵州重庆等地大到暴雨将成片出没 明起华北东北降雨再度增多", "content": "今明天（7月17日至18日），我国较强降雨带将呈现逐步南压的趋势，贵州、重庆等地雨势明显加强，大到暴雨连成片，与此同时，华北、东北降雨将再度增多。随着降雨发展、副热带高压减弱，今天起南方持续盘踞的高温将快速收敛，闷热感得到缓和。\n贵州重庆等地大到暴雨将成片出没 华北东北降雨再度增多\n昨天，降雨主要围绕副热带高压边缘发展，四川盆地至黄淮、江淮北部形成一条较强的降雨带。监测显示，昨天山西南部、河南北部、陕西中南部、甘肃南部、四川中部、重庆北部、安徽北部、广西南部、广东中部沿海等地部分地区出现暴雨或大暴雨。\n由于副热带高压减弱南撤，今明天雨带将呈现逐步南压的趋势，贵州、重庆等地雨势会明显加强，大到暴雨连成片；广东、广西等地受到季风槽的影响，局地雨势依旧强劲。此外，华北、东北明起降雨将再度发展增多。\n中央气象台预计，今天山东中南部、河南东部和南部、苏皖北部、湖北东北部和中西部、四川南部、重庆、贵州西部和北部、云南东部和南部、广西西部和中南部、广东南部等地部分地区有大到暴雨，其中，山东南部、江苏北部、湖北东北部和西南部、重庆中部等地部分地区有大暴雨。\n明天，内蒙古东南部、西藏东南部、京津冀、苏皖南部、湖北南部、江西中北部、湖南、贵州、云南、广西、广东等地部分地区有中到大雨，其中，西藏东南部、湖南西部、江西北部、重庆东南部、贵州东北部和西南部、云南中西部、广西西北部等地部分地区有暴雨或大暴雨。\n后天，苏皖南部、湖北东部、江西中北部、湖南西部和北部、贵州东南部、云南中南部、广西、广东等地部分地区有中到大雨，其中，湖南中西部、江西北部、贵州东南部、云南南部、广西西部和东北部等地部分地区有暴雨或大暴雨。\n气象专家提醒，今后几天，我国强降雨区分散，呈现面广点强的特征，公众需警惕局地强降雨或持续降雨可能引发的滑坡、泥石流等次生灾害，尽量避免前往山区、河谷等地质灾害隐患点。\n近日，南方暑热“火力全开”，多地开启全天候闷热模式，重庆沙坪坝最低气温达33.5℃，追平当地7月夜温最高纪录；上海徐家汇最低气温31.6℃，追平当地7月中旬夜温最高纪录。昨天白天，高温范围依然广泛，四川、重庆等地局地气温达到40℃以上。\n今天起，随着副热带高压减弱东退，降雨增多，持续盘踞南方的高温也会快速收敛，各地陆续退出高温行列。像武汉、长沙，最高气温将从35℃以上降到30℃左右，闷热感得到缓和。\n不过，南方高温消退的同时，受伊朗高压东伸与大陆高压叠加影响，西北地区高温将发展增强，明起至21日乌鲁木齐气温可能频繁创今年以来新高，当地公众要继续做好防暑降温措施，谨防中暑。", "published_time": "2026-07-17 08:56", "metrics": [], "paragraph_count": 11, "truncated": false, "fetched_at": "2026-07-17T15:02:27.064515+08:00", "cache_hit": false}