{"ok": true, "status": 200, "final_url": "http://www.ce.cn/xwzx/gnsz/gdxw/202607/t20260721_3098950.shtml", "page_title": "“国家队”600亿增持中国股票！涌入这三大方向→_中国经济网——国家经济门户", "summary": "“国家队”600亿增持中国股票！涌入这三大方向→", "content": "7月19日，中国国新、中国诚通两大国资运营平台连夜发声，超600亿资金入场，中国证监会今天召开稳市场专题座谈会，中国神华、中国中车等五大央企盘前发声，回购、增持、分红，此时此刻，这些动作连起来看，释放明显信号，用“真金白银”表达信心。\n他们是“资本市场维稳的国家队”，手头有国家大基金、央企股权和不少低成本流动资金。\n国新在公告中用了两个坚决：“坚决维护资本市场核心资产战略价值，坚决维护资本市场平稳健康运行。”\n三个关键词，优质央企、优质科技资产和宽基ETF。同时，这次出手还有两大特点，定向支持，长期持有。背后的信号很明显——买核心资产、坚定支持科技创新、快速传导流动性到全市场和长期看好中国的核心资产。\n如果把视线拉长来看，国家队此次“真金白银”的集结，绝非一次短暂的“救火”，而是展现“工具箱”灵活、后续“弹药”充足、稳定信心的长期持有。\n近期宏观数据稳健增长，制造业景气度持续回暖，高技术制造业投资增速更是领跑全局。来看外资聪明钱的选择，从一季度投资数据来看，外资也在持续买入中国好资产。比如阿布扎比投资局，买的A股数量从去年的24只翻倍成一季度54只，重仓有色金属、消费电子和半导体龙头。\n有经济底子、有国家队“耐心资本”的长期注入，有外资持续加仓，投资者要做的就是顺大势而为，“择优、长持、保持信心”。\n近期多家上市公司和券商相继披露股份回购计划，上周末，沪深两市共有55家公司披露增持回购相关公告，其中14家公司披露新增增持回购计划，持续向市场传递长期发展信心。\n中国铝业控股股东中铝集团及其一致行动人计划未来12个月增持公司A股及H股，金额不低于10亿元、不超过20亿元；\n中国中车控股股东中车集团计划未来6个月增持公司A股，金额不低于1.5亿元、不超过3亿元；\n中煤能源控股股东中国中煤计划增持5000万元至1亿元。\n国电南瑞拟使用5亿元至10亿元自有资金回购股份。\n中国神华表示将保持现金分红频次，继续开展中期分红，稳定回报股东。\n华安证券、国联民生分别推出1亿元至2亿元回购方案。\n荣昌生物、建龙微纳等科创板公司也相继推出回购计划。\n7月以来，沪深两市已有469家次公司披露回购增持相关公告，其中新增回购增持计划113家次，计划回购增持上限合计超过157亿元，上市公司回购增持力度持续提升。\n今天，多家保险公司同样发布声明，坚定看好中国资本市场发展前景，以实际行动积极把握资本市场估值修复与产业成长双重机遇，看好中国权益市场长期配置价值。", "published_time": "2026-07-21 10:53", "metrics": [], "paragraph_count": 17, "truncated": false, "fetched_at": "2026-07-21T11:37:48.180145+08:00", "cache_hit": false}