{"ok": true, "status": 200, "final_url": "https://m.21jingji.com/article/20260720/herald/00ba3cc4a523fe53b5cf5a2026c186b7.html", "page_title": "马来西亚纳闽金融中心中国办主任：金融护航中企全球化布局 - 21财经", "summary": "南方财经 21世纪经济报道记者胡慧茵 报道当前，中国企业出海正从产品、产能出海，逐步迈向产业链供应链出海的新阶段。“今天很多中国企业出海是在进行更深层次的全球化布局。”近日，马来西亚纳闽金融中心中国业...", "content": "南方财经 21世纪经济报道记者胡慧茵 报道\n当前，中国企业出海正从产品、产能出海，逐步迈向产业链供应链出海的新阶段。\n“今天很多中国企业出海是在进行更深层次的全球化布局。”近日，马来西亚纳闽金融中心中国业务办主任廖予嫣在接受21世纪经济报道记者采访时说。谈及中国企业出海在金融方面的需求，她指出，这些需求涉及海外投资、区域总部设立、生产基地建设、贸易结算、融资安排和风险管理等领域。\n在廖予嫣看来，马来西亚纳闽国际商业金融中心与致力于出海业务的中国企业有着天然的业务互补性，合作前景广阔。她表示，首先，纳闽金融中心是中国企业连接东盟和全球市场的平台。纳闽国际商业金融中心位于马来西亚，马来西亚本身是东盟重要的成员国，也是连接中国、东盟、中东等全球主要市场的重要节点。对于希望拓展东盟和国际市场的中国企业来说，纳闽金融中心可以作为区域投资、贸易和金融安排的平台。\n其次，马来西亚具有完整的国际商业金融生态。纳闽金融中心在马来西亚纳闽金融管理局的监管下，形成了涵盖多种业态的金融生态，包括银行、保险、自保、伊斯兰金融、数字金融和公司架构服务。因此，纳闽金融中心可以为中企提供项目融资、结构化融资、贸易融资、司库管理等金融服务，有助于中企建立更加清晰的跨境资金安排。\n再者，纳闽国际商业金融中心强调合规监管和长期的可持续发展。现在很多出海的中国企业越来越重视合规、税务透明、实质经营和风险管控，而金融中心可以为它们提供一个受监管、透明合规、可持续使用的国际金融和商业平台。\n廖予嫣认为，在这个过程中，纳闽金融中心可以为中企出海搭建起桥梁和平台，让中企进一步拓展马来西亚乃至全球市场。\n（作者：胡慧茵 编辑：和佳,视频制作,李群,设计,王冰）\n南方财经全媒体集团及其客户端所刊载内容的知识产权均属其旗下媒体。未经书面授权，任何人不得以任何方式使用。详情或获取授权信息请点击此处。\n长期关注日韩和东南亚等区域的热点时事动态，掌握海外市场一手资讯。", "published_time": "2026-07-20 21:28", "metrics": [], "paragraph_count": 10, "truncated": false, "fetched_at": "2026-07-21T11:38:06.088105+08:00", "cache_hit": false}