{"ok": true, "status": 200, "final_url": "http://www.ce.cn/xwzx/gnsz/gdxw/202607/t20260717_3092843.shtml", "page_title": "山东胶州：丝路长歌，一城夏意_中国经济网——国家经济门户", "summary": "山东胶州：丝路长歌，一城夏意", "content": "“上午打卡《丝路千古情》实景演艺，沉浸式感受丝路文脉；傍晚走进上合之珠国际博览中心，一日游历二十国；入夜纵享啤酒狂欢，于湖畔寻鹅探秘；次日步入大沽河博物馆，品读千年古埠的岁月变迁……”\n7月15日，“丝路长歌 燃动盛夏”胶州市2026年暑期文旅体商活动新闻发布会举行，现场集中发布五大板块45项特色活动，同步推出三条精品游玩线路。\n暑期，山东省胶州市以“丝路千古情”这一全新文旅IP为牵引，统筹整合文旅、体育、商业等多领域资源，构建日夜联动、文旅商体融合的夏日游玩体系，持续释放暑期文旅消费潜力。\n6月26日，位于上合示范区核心区的丝路千古情景区正式开幕。作为“千古情”系列在山东的首个项目、青岛市首座沉浸式全域演艺公园，景区开园即成为城市夏日文旅新热点。\n“景区打破了传统文旅项目单一观光的模式，让丝路文化可观、可感、可体验。”青岛上合文旅产业有限公司总经理汤宇超在发布会上介绍。立足胶州板桥镇千年海上丝路底蕴，景区深度融合齐鲁文脉、海上丝路文化与上合多国风情，运用全息投影、实景特效和沉浸式街区，打造全天候游览场景。\n暑期园区根据客流量动态调整闭园时间，5.1万平方米的沉浸式主题街区全天候轮番上演上百场街头演艺。核心演艺《丝路千古情》串起海岱文明、齐风鲁韵、板桥通商、法显求法等历史篇章，一张门票畅享全天演艺。\n走出景区，步行即达上合之珠国际博览中心。20个上合组织国家主题展馆开放参观，各国风情、特色文创、研学课程一站式体验；大沽河博物馆同步推出“行走的博物馆”移动展览，与上合之珠联动打卡；如意湖开设快艇观光项目，帆船赛事常态化举办。\n7月22日，“寻味上合·丝路盛宴”—“国信水产·裕鲜舫杯”创新菜品技能大赛将在上合建国饭店开赛。36名本地厨师围绕胶州大白菜、里岔黑猪等地标食材同台竞技。\n“观演之后，‘胶州味道’静候品鉴。”胶州市文化和旅游局局长陈文超表示。\n7月25日至8月2日，“与湖造浪”2026胶州啤酒音乐节将在龙湖天街举行。活动以“音乐节+啤酒市集”形式呈现，设置国际啤酒品饮、美食市集、文创后备箱三大板块，知名歌手现场献唱。\n为畅通“游”与“娱”的衔接，“丝路千古情”景区开通“日游丝路、夜嗨啤酒”交通接驳专线，游客白天看秀后，可乘车直达青岛国际啤酒节及胶州市区，白天看秀、夜间畅饮、全程无忧。\n青岛大沽河省级生态旅游度假区将于8月6日至9日推出“寻鹅记之夏夜之梦”活动。延续寻鹅故事主线，活动以天鹅入梦、泡泡造境为创意核心，设幻境、奇境、秘境、梦境四大主题空间，巡游演艺、天幕市集、文创手作穿插其间，面向市民游客免费开放。\n“天鹅、梦境、烟火气，少海之夜，邀您共赏。”青岛大沽河省级生态旅游度假区党工委委员、管委会副主任李汉帅说。\n夏日消费，也有“清凉”补贴。胶州市商务局副局长庄春晓介绍，餐饮消费抽奖活动已开启，单笔餐饮消费满100元即可参与抽奖。面向大学新生的3C数码以旧换新活动同步启动，涵盖电脑、手机、平板等品类，部分机型可叠加分期免息优惠。\n发布会上，三条精品旅游线路同步发布，覆盖研学、慢享、康养三大主题，有机串联全市文旅资源。\n“丝路博览·研学求知”线路串联千古情、上合之珠、大沽河博物馆、民航博物馆等，深度品读海丝历史；“湖光非遗·乡野慢享”线路串联少海、高凤翰纪念馆、兴郭手造村、曹家庄等，主打近郊清凉微度假；“田园栖居·康养休闲”线路串联祓泽湖、桃源居、如意湖等，一站式解锁田园慢生活。\n惠民活动贯穿整夏。大沽河博物馆、高凤翰纪念馆、市美术馆等文化场馆免票开放，高凤翰纪念馆展出省级非遗蛋壳黑陶精品，市美术馆展出80余幅名家作品。广场文艺周周演7至10月常态化上演，非遗夜校每晚免费授课，市民游客可就近参与。\n“工唱胶州”职工歌唱艺术节已开放线上报名，不限年龄、不限岗位，总决赛将在市民广场激情上演。“报名通道已通过‘胶州市总工会’微信公众号和齐鲁工惠APP同步开启，欢迎全市职工踊跃参与，唱响劳动之歌！”胶州市总工会党组成员、副主席祁喜庆说。\n“从一场秀到一座城，我们诚挚邀请全国各地游客走进胶州，畅游城乡美景，共赴丝路长歌！”陈文超发出邀请。", "published_time": "2026-07-17 14:18", "metrics": [], "paragraph_count": 19, "truncated": false, "fetched_at": "2026-07-17T15:03:07.269249+08:00", "cache_hit": false}