{"ok": true, "status": 200, "final_url": "https://www.yicai.com/news/103285230.html", "page_title": "匈牙利国际象棋大师波尔加尔谢绝出任总统", "summary": "波尔加尔表示，自身尚不具备承担“这一历史性责任”所需的能力，因此决定婉拒提名。", "content": "打开微信，点击底部的“发现”，使用“扫一扫”即可将网页分享至朋友圈。\n新华社2026-07-21 10:34:35\n匈牙利女子国际象棋大师波尔加尔·尤迪特20日在社交媒体发文称，已谢绝总理毛焦尔对其出任下一任总统的邀请。\n波尔加尔表示，自身尚不具备承担“这一历史性责任”所需的能力，因此决定婉拒提名。\n19日，16名来自匈牙利科学、文化和体育界知名人士联名致信国会主席福斯特霍费尔·阿格奈什，提议推举波尔加尔为匈牙利总统。随后，毛焦尔在社交媒体表示，将会见波尔加尔并邀请她出任总统。\n匈牙利时任总统舒尤克18日宣布签署《基本法》修正案，结束其任期，国会将于30天内选举产生新总统。在新总统就职前，福斯特霍费尔暂时行使国家元首的职权。\n匈牙利新政府面临一项微妙的任务：既要获取180亿欧元的欧盟资金，又要保留至关重要的中国投资，同时需应对日益严格的欧洲监管审查。\n白宫已经向国会参议院提交关于凯文·沃什担任美国联邦储备委员会下一任主席的提名。\n“特朗普本就把向乌克兰提供‘战斧’导弹作为向俄方施压的手段。”\n特朗普将先和泽连斯基会谈，而后与到访的欧洲领导人举行集体会晤。", "published_time": "2026-07-21 10:34:35", "metrics": [{"metric": "comments", "value": 7, "source": "dom_class", "confidence": "high", "evidence": "7"}], "paragraph_count": 10, "truncated": false, "fetched_at": "2026-07-21T11:37:57.188017+08:00", "cache_hit": false}