{"ok": true, "status": 200, "final_url": "https://www.sohu.com/a/1051178154_120988533?scm=10001.327_13-327_13-61_61.0-0.0-0-0-0-0.0", "page_title": "首页", "summary": "根据公司此前公布的回拨机制，由于本次网上发行初步有效申购倍数约为243.93倍，超过100倍，发行人和联席主承销商决定启动回拨机制，对网下、网上发行的规模进行调节，将扣除最终战略配售部分后本次公开发行股票数量…", "content": "7月16日晚，长鑫科技公布网上发行申购情况及中签率公告。公告显示，本次发行价格为8.66元/股，网上发行有效申购户数为9428778户，有效申购股数为8169.20亿股。回拨机制启动后，网上最终发行数量为385110.35万股，网上发行最终中签率约为0.47141739%。\n回拨机制，通俗概括讲就是，如果网上申购的人太多，将把一部分网下发行额度调整到网上来发行。\n根据公司此前公布的回拨机制，由于本次网上发行初步有效申购倍数约为243.93倍，超过100倍，发行人和联席主承销商决定启动回拨机制，对网下、网上发行的规模进行调节，将扣除最终战略配售部分后本次公开发行股票数量的10%（向上取整至500股的整数倍，即50210.2500万股）从网下回拨至网上。\n根据公告，在超额配售选择权及网上、网下回拨机制启动后，网下最终发行数量为217313.3388万股，约占超额配售选择权全额行使后扣除最终战略配售数量后发行数量的36.07%，约占超额配售选择权全额行使后发行数量的28.25%；网上最终发行数量为385110.3500万股，约占超额配售选择权全额行使后扣除最终战略配售数量后发行数量的63.93%，约占超额配售选择权全额行使后发行数量的50.07%。\n回拨机制启动后，网上发行最终中签率为0.47141739%。\n由于发行体量大，长鑫科技本次网上发行数量相应增加。此前，据多家机构综合测算，其网上中签率预计将落在0.3%—0.7%的区间内。\n与已上市的科创板公司相比，长鑫科技此次中签率处于何种区间？\n根据Wind统计，科创板超600家上市公司中，网上申购中签率高于0.1%的有10家，其中，超0.2%的有4家，分别是和辉光电（0.3031%）、芯联集成（0.2456%）、中国通号（0.2254%）、中芯国际（0.2120%）。\n从中位数来看，已上市科创板公司的网上申购中签率0.0363%。由此来看，长鑫科技属于高中签率水平。\n此前，长鑫科技网下询价十分“火热”。根据此前公告，长鑫科技询价阶段共收到333家网下投资者管理的11537个配售对象的初步询价报价信息，报价区间为7.26元/股—65.19元/股，拟申购数量总和为12860.62亿股。\n剔除无效报价、最高报价以及低于发行价的报价后，长鑫科技本次网下发行提交有效报价的网下投资者数量为285家，管理的配售对象数量为10907个，有效拟申购数量总和为12382.22亿股，约为战略配售回拨前网下初始发行规模的462.85倍。\n市场人士认为，未来一年多内，长鑫科技有望逐步被纳入从行业主题指数到核心宽基指数的各层级指数体系，这将为其带来可观的增量投资资金，同时提升相关指数的底层资产质量和投资价值。\n业绩层面，2026年第一季度，长鑫科技实现了508亿元的营业收入和超263亿元的扣非后净利润，同比增长719%和1993%。公司预计上半年营业收入为1100亿元至1200亿元，归母净利润为500亿元至570亿元。返回搜狐，查看更多", "published_time": "2026-07-16 19:45", "metrics": [], "paragraph_count": 13, "truncated": false, "fetched_at": "2026-07-17T15:15:33.851697+08:00", "cache_hit": false}