{"ok": true, "status": 200, "final_url": "https://finance.ifeng.com/c/8unetU3kqQ1", "page_title": "日本股市跌超1700点，韩国股市狂泻超400点，跌到熔断", "summary": "日本股市跌超1700点，韩国股市狂泻超400点，跌到熔断", "content": "7月16日，日韩股市集体跳水。截至发稿，韩国KOSPI综指跌5.75%，三星电子跌超6%、SK海力士跌超10%。日经225指数跌超2.5%。\n韩国交易所启动“SIDECAR”机制，暂停KOSPI程序化交易。\n隔夜美股三大指数集体收涨，道指涨0.29%，纳指涨0.62%，标普500指数涨0.38%，但存储概念股、计算机硬件板块逆市大跌，SK海力士跌超9%，美光科技、闪迪、西部数据跌超8%，AMD、惠普跌超3%。\n“特别声明：以上作品内容(包括在内的视频、图片或音频)为凤凰网旗下自媒体平台“大风号”用户上传并发布，本平台仅提供信息存储空间服务。\nNotice: The content above (including the videos, pictures and audios if any) is uploaded and posted by the user of Dafeng Hao, which is a social media platform and merely provides information storage space services.”\n您当前使用的浏览器版本过低，导致网站不能正常访问，建议升级浏览器", "published_time": "2026年07月16日 08:29:41", "metrics": [], "paragraph_count": 6, "truncated": false, "fetched_at": "2026-07-16T11:18:03.110521+08:00", "cache_hit": false}